odoo/addons/shopinvader_api_cart/README.rst
odoo/addons/shopinvader_api_cart/__init__.py
odoo/addons/shopinvader_api_cart/__manifest__.py
odoo/addons/shopinvader_api_cart/hooks.py
odoo/addons/shopinvader_api_cart/i18n/shopinvader_api_cart.pot
odoo/addons/shopinvader_api_cart/migrations/16.0.1.0.1/pre-migrate.py
odoo/addons/shopinvader_api_cart/models/__init__.py
odoo/addons/shopinvader_api_cart/models/sale_order.py
odoo/addons/shopinvader_api_cart/readme/CONTRIBUTORS.rst
odoo/addons/shopinvader_api_cart/readme/DESCRIPTION.rst
odoo/addons/shopinvader_api_cart/readme/HISTORY.rst
odoo/addons/shopinvader_api_cart/readme/USAGE.rst
odoo/addons/shopinvader_api_cart/readme/newsfragments/.gitignore
odoo/addons/shopinvader_api_cart/routers/__init__.py
odoo/addons/shopinvader_api_cart/routers/cart.py
odoo/addons/shopinvader_api_cart/schemas/__init__.py
odoo/addons/shopinvader_api_cart/schemas/cart.py
odoo/addons/shopinvader_api_cart/schemas/sale.py
odoo/addons/shopinvader_api_cart/security/acl_ir_sequence.xml
odoo/addons/shopinvader_api_cart/static/description/index.html
odoo/addons/shopinvader_api_cart/tests/__init__.py
odoo/addons/shopinvader_api_cart/tests/common.py
odoo/addons/shopinvader_api_cart/tests/test_shopinvader_api_cart.py
odoo_addon_shopinvader_api_cart-16.0.1.5.0.dist-info/METADATA
odoo_addon_shopinvader_api_cart-16.0.1.5.0.dist-info/WHEEL
odoo_addon_shopinvader_api_cart-16.0.1.5.0.dist-info/top_level.txt
odoo_addon_shopinvader_api_cart-16.0.1.5.0.dist-info/RECORD
